plover_melani/__init__.py
plover_melani/system.py
plover_melani/theory.py
plover_melani/dictionaries/melani_main.json
plover_melani/dictionaries/melani_orthography.json
plover_melani/dictionaries/melani_orthography.py
plover_melani/dictionaries/melani_user.json
plover_melani/scripts/__init__.py
plover_melani/scripts/sortdict.py
plover_melani/scripts/testortho.py
plover_melani/scripts/voc2json.py
plover_melani-0.6.0.dist-info/METADATA
plover_melani-0.6.0.dist-info/WHEEL
plover_melani-0.6.0.dist-info/entry_points.txt
plover_melani-0.6.0.dist-info/top_level.txt
plover_melani-0.6.0.dist-info/zip-safe
plover_melani-0.6.0.dist-info/RECORD
