Metadata-Version: 2.1
Name: plover-melani
Version: 0.6.0
Summary: Melani (Italian system) support for Plover
Home-page: https://github.com/benoit-pierre/plover_melani
Author: Benoit Pierre
Author-email: benoit.pierre@gmail.com
License: GNU General Public License v2 or later (GPLv2+)
Project-URL: Source Code, https://github.com/benoit-pierre/plover_melani
Project-URL: Issue Tracker, https://github.com/benoit-pierre/plover_melani/issues
Keywords: plover plover_plugin
Platform: UNKNOWN
Classifier: Development Status :: 4 - Beta
Classifier: Environment :: Plugins
Classifier: Intended Audience :: End Users/Desktop
Classifier: License :: OSI Approved :: GNU General Public License v2 or later (GPLv2+)
Classifier: Operating System :: OS Independent
Classifier: Programming Language :: Python :: 3
Classifier: Programming Language :: Python :: 3.6
Classifier: Programming Language :: Python :: 3.7
Classifier: Programming Language :: Python :: 3.8
Classifier: Programming Language :: Python :: 3.9
Requires-Python: >=3.6
Requires-Dist: plover (>=4.0.0.dev9)
Requires-Dist: plover-stroke (>=0.4.0)
Requires-Dist: plover-python-dictionary (>=0.5.6)
Provides-Extra: test
Requires-Dist: plover (>=4.0.0.dev9) ; extra == 'test'
Requires-Dist: pytest (>=3.0.1) ; extra == 'test'
